Metadata-Version: 2.1
Name: lingy
Version: 0.0.1
Summary: Program in YAML
Home-page: https://github.com/ingydotnet/lingy
Author: Ingy döt Net
Author-email: ingy@ingy.net
License: MIT
Keywords: yaml,language
Platform: UNKNOWN
Classifier: Development Status :: 3 - Alpha
Classifier: Intended Audience :: Developers
Classifier: License :: OSI Approved :: MIT License
Classifier: Programming Language :: Python :: 3
Classifier: Programming Language :: Python :: 3.6
Classifier: Programming Language :: Python :: 3.7
Classifier: Programming Language :: Python :: 3.8
Classifier: Programming Language :: Python :: 3.9
Classifier: Programming Language :: Python :: 3 :: Only
Requires-Python: >=3.6, <4
